simWorkspace/StreamPayloadSplit/rtl/StreamPayloadSplit.v
// Generator : SpinalHDL v1.6.0    git head : 73c8d8e2b86b45646e9d0b2e729291f2b65e6be3
// Component : StreamPayloadSplit
// Git hash  : 8096539601639817b14f806164427f8ddd4d6b02



module StreamPayloadSplit (
  input               raw_data_valid,
  output              raw_data_ready,
  input      [31:0]   raw_data_payload,
  output              split_data_valid,
  input               split_data_ready,
  output     [7:0]    split_data_payload,
  input               clk,
  input               reset
);
  reg        [2:0]    cnt;
  reg        [31:0]   data_buf;
  wire                raw_data_fire;
  wire                split_data_fire;

  assign raw_data_fire = (raw_data_valid && raw_data_ready);
  assign split_data_fire = (split_data_valid && split_data_ready);
  assign raw_data_ready = (cnt == 3'b000);
  assign split_data_valid = (cnt != 3'b000);
  assign split_data_payload = data_buf[31 : 24];
  always @(posedge clk or posedge reset) begin
    if(reset) begin
      cnt <= 3'b000;
    end else begin
      if(raw_data_fire) begin
        cnt <= 3'b100;
      end else begin
        if(split_data_fire) begin
          cnt <= (cnt - 3'b001);
        end
      end
    end
  end

  always @(posedge clk) begin
    if(raw_data_fire) begin
      data_buf <= raw_data_payload;
    end else begin
      if(split_data_fire) begin
        data_buf <= (data_buf <<< 8);
      end
    end
  end


endmodule

simWorkspace/StreamPayloadSplit/test.vcd
$version Generated by VerilatedVcd $end
$date Tue Oct 26 20:46:23 2021
 $end
$timescale   1ns $end

 $scope module TOP $end
  $var wire  1 s clk $end
  $var wire 32 S raw_data_payload [31:0] $end
  $var wire  1 K raw_data_ready $end
  $var wire  1 C raw_data_valid $end
  $var wire  1 { reset $end
  $var wire  8 k split_data_payload [7:0] $end
  $var wire  1 c split_data_ready $end
  $var wire  1 [ split_data_valid $end
  $scope module StreamPayloadSplit $end
   $var wire  1 s clk $end
   $var wire  3 ; cnt [2:0] $end
   $var wire 32 3 data_buf [31:0] $end
   $var wire  1 # raw_data_fire $end
   $var wire 32 S raw_data_payload [31:0] $end
   $var wire  1 K raw_data_ready $end
   $var wire  1 C raw_data_valid $end
   $var wire  1 { reset $end
   $var wire  1 + split_data_fire $end
   $var wire  8 k split_data_payload [7:0] $end
   $var wire  1 c split_data_ready $end
   $var wire  1 [ split_data_valid $end
  $upscope $end
 $upscope $end
$enddefinitions $end


#0
0#
0+
b11000111110010111010100011000001 3
b000 ;
0C
1K
b11000100111111011111010111011101 S
0[
1c
b11000111 k
0s
1{
#80
0{
#85
1#
1C
b00000000000000000000000000000001 S
1s
#87
0s
#89
0#
1+
b00000000000000000000000000000001 3
b100 ;
0K
b00000000000000000000000000000010 S
1[
b00000000 k
1s
#91
0s
#93
b00000000000000000000000100000000 3
b011 ;
b00000000000000000000000000000011 S
1s
#95
0s
#97
b00000000000000010000000000000000 3
b010 ;
b00000000000000000000000000000100 S
1s
#99
0s
#101
b00000001000000000000000000000000 3
b001 ;
b00000000000000000000000000000001 S
b00000001 k
1s
#103
0s
#105
1#
0+
b00000000000000000000000000000000 3
b000 ;
1K
b00000000000000000000000000000010 S
0[
b00000000 k
1s
#107
0s
#109
0#
1+
b00000000000000000000000000000010 3
b100 ;
0K
b00000000000000000000000000000011 S
1[
1s
#111
0s
#113
b00000000000000000000001000000000 3
b011 ;
b00000000000000000000000000000100 S
1s
#115
0s
#117
b00000000000000100000000000000000 3
b010 ;
b00000000000000000000000000000001 S
1s
#119
0s
#121
b00000010000000000000000000000000 3
b001 ;
b00000000000000000000000000000010 S
b00000010 k
1s
#123
0s
#125
1#
0+
b00000000000000000000000000000000 3
b000 ;
1K
b00000000000000000000000000000011 S
0[
b00000000 k
1s
#127
0s
#129
0#
1+
b00000000000000000000000000000011 3
b100 ;
0K
b00000000000000000000000000000100 S
1[
1s
#131
0s
#133
b00000000000000000000001100000000 3
b011 ;
b00000000000000000000000000000001 S
1s
#135
0s
#137
b00000000000000110000000000000000 3
b010 ;
b00000000000000000000000000000010 S
1s
#139
0s
#141
b00000011000000000000000000000000 3
b001 ;
b00000000000000000000000000000011 S
b00000011 k
1s
#143
0s
#145
1#
0+
b00000000000000000000000000000000 3
b000 ;
1K
b00000000000000000000000000000100 S
0[
b00000000 k
1s
#147
0s
#149
0#
1+
b00000000000000000000000000000100 3
b100 ;
0K
b00000000000000000000000000000001 S
1[
1s
#151
0s
#153
b00000000000000000000010000000000 3
b011 ;
b00000000000000000000000000000010 S
1s
#155
0s
#157
b00000000000001000000000000000000 3
b010 ;
b00000000000000000000000000000011 S
1s
#159
0s
#161
b00000100000000000000000000000000 3
b001 ;
b00000000000000000000000000000100 S
b00000100 k
1s
#163
0s
#165
1#
0+
b00000000000000000000000000000000 3
b000 ;
1K
b00000000000000000000000000000001 S
0[
b00000000 k
1s
#167
0s
#169
0#
1+
b00000000000000000000000000000001 3
b100 ;
0K
b00000000000000000000000000000010 S
1[
1s
#171
0s
#173
b00000000000000000000000100000000 3
b011 ;
b00000000000000000000000000000011 S
1s
#175
0s
#177
b00000000000000010000000000000000 3
b010 ;
b00000000000000000000000000000100 S
1s
#179
0s
#181
b00000001000000000000000000000000 3
b001 ;
b00000000000000000000000000000001 S
b00000001 k
1s
#183
0s
#185
1#
0+
b00000000000000000000000000000000 3
b000 ;
1K
b00000000000000000000000000000010 S
0[
b00000000 k
1s
#187
0s
#189
0#
1+
b00000000000000000000000000000010 3
b100 ;
0K
b00000000000000000000000000000011 S
1[
1s
#191
0s
#193
b00000000000000000000001000000000 3
b011 ;
b00000000000000000000000000000100 S
1s
#195
0s
#197
b00000000000000100000000000000000 3
b010 ;
b00000000000000000000000000000001 S
1s
#199
0s
#201
b00000010000000000000000000000000 3
b001 ;
b00000000000000000000000000000010 S
b00000010 k
1s
#203
0s
#205
1#
0+
b00000000000000000000000000000000 3
b000 ;
1K
b00000000000000000000000000000011 S
0[
b00000000 k
1s
#207
0s
#209
0#
1+
b00000000000000000000000000000011 3
b100 ;
0K
b00000000000000000000000000000100 S
1[
1s
#211
0s
#213
b00000000000000000000001100000000 3
b011 ;
b00000000000000000000000000000001 S
1s
#215
0s
#217
b00000000000000110000000000000000 3
b010 ;
b00000000000000000000000000000010 S
1s
#219
0s
#221
b00000011000000000000000000000000 3
b001 ;
b00000000000000000000000000000011 S
b00000011 k
1s
#223
0s
#225
1#
0+
b00000000000000000000000000000000 3
b000 ;
1K
b00000000000000000000000000000100 S
0[
b00000000 k
1s
#227
0s
#229
0#
1+
b00000000000000000000000000000100 3
b100 ;
0K
b00000000000000000000000000000001 S
1[
1s
#231
0s
#233
b00000000000000000000010000000000 3
b011 ;
b00000000000000000000000000000010 S
1s
#235
0s
#237
b00000000000001000000000000000000 3
b010 ;
b00000000000000000000000000000011 S
1s
#239
0s
#241
b00000100000000000000000000000000 3
b001 ;
b00000000000000000000000000000100 S
b00000100 k
1s
#243
0s
#245
1#
0+
b00000000000000000000000000000000 3
b000 ;
1K
b00000000000000000000000000000001 S
0[
b00000000 k
1s
#247
0s
#249
0#
1+
b00000000000000000000000000000001 3
b100 ;
0K
b00000000000000000000000000000010 S
1[
1s
#251
0s
#253
b00000000000000000000000100000000 3
b011 ;
b00000000000000000000000000000011 S
1s
#255
0s
#257
b00000000000000010000000000000000 3
b010 ;
b00000000000000000000000000000100 S
1s
#259
0s
#261
b00000001000000000000000000000000 3
b001 ;
b00000000000000000000000000000001 S
b00000001 k
1s
#263
0s
#265
1#
0+
b00000000000000000000000000000000 3
b000 ;
1K
b00000000000000000000000000000010 S
0[
b00000000 k
1s
#267
0s
#269
0#
1+
b00000000000000000000000000000010 3
b100 ;
0K
b00000000000000000000000000000011 S
1[
1s
#271
0s
#273
b00000000000000000000001000000000 3
b011 ;
b00000000000000000000000000000100 S
1s
#275
0s
#277
b00000000000000100000000000000000 3
b010 ;
b00000000000000000000000000000001 S
1s
#279
0s
#281
b00000010000000000000000000000000 3
b001 ;
b00000000000000000000000000000010 S
b00000010 k
1s
#283
0s
#285
1#
0+
b00000000000000000000000000000000 3
b000 ;
1K
b00000000000000000000000000000011 S
0[
b00000000 k
1s
#287
0s
#289
0#
1+
b00000000000000000000000000000011 3
b100 ;
0K
b00000000000000000000000000000100 S
1[
1s
#291
0s
#293
b00000000000000000000001100000000 3
b011 ;
b00000000000000000000000000000001 S
1s
#295
0s
#297
b00000000000000110000000000000000 3
b010 ;
b00000000000000000000000000000010 S
1s
#299
0s
#301
b00000011000000000000000000000000 3
b001 ;
b00000000000000000000000000000011 S
b00000011 k
1s
#303
0s
#305
1#
0+
b00000000000000000000000000000000 3
b000 ;
1K
b00000000000000000000000000000100 S
0[
b00000000 k
1s
#307
0s
#309
0#
1+
b00000000000000000000000000000100 3
b100 ;
0K
b00000000000000000000000000000001 S
1[
1s
#311
0s
#313
b00000000000000000000010000000000 3
b011 ;
b00000000000000000000000000000010 S
1s
#315
0s
#317
b00000000000001000000000000000000 3
b010 ;
b00000000000000000000000000000011 S
1s
#319
0s
#321
b00000100000000000000000000000000 3
b001 ;
b00000000000000000000000000000100 S
b00000100 k
1s
#323
0s
#325
1#
0+
b00000000000000000000000000000000 3
b000 ;
1K
b00000000000000000000000000000001 S
0[
b00000000 k
1s
#327
0s
#329
0#
1+
b00000000000000000000000000000001 3
b100 ;
0K
b00000000000000000000000000000010 S
1[
1s
#331
0s
#333
b00000000000000000000000100000000 3
b011 ;
b00000000000000000000000000000011 S
1s
#335
0s
#337
b00000000000000010000000000000000 3
b010 ;
b00000000000000000000000000000100 S
1s
#339
0s
#341
b00000001000000000000000000000000 3
b001 ;
b00000000000000000000000000000001 S
b00000001 k
1s
#343
0s
#345
1#
0+
b00000000000000000000000000000000 3
b000 ;
1K
b00000000000000000000000000000010 S
0[
b00000000 k
1s
#347
0s
#349
0#
1+
b00000000000000000000000000000010 3
b100 ;
0K
b00000000000000000000000000000011 S
1[
1s
#351
0s
#353
b00000000000000000000001000000000 3
b011 ;
b00000000000000000000000000000100 S
1s
#355
0s
#357
b00000000000000100000000000000000 3
b010 ;
b00000000000000000000000000000001 S
1s
#359
0s
#361
b00000010000000000000000000000000 3
b001 ;
b00000000000000000000000000000010 S
b00000010 k
1s
#363
0s
#365
1#
0+
b00000000000000000000000000000000 3
b000 ;
1K
b00000000000000000000000000000011 S
0[
b00000000 k
1s
#367
0s
#369
0#
1+
b00000000000000000000000000000011 3
b100 ;
0K
b00000000000000000000000000000100 S
1[
1s
#371
0s
#373
b00000000000000000000001100000000 3
b011 ;
b00000000000000000000000000000001 S
1s
#375
0s
#377
b00000000000000110000000000000000 3
b010 ;
b00000000000000000000000000000010 S
1s
#379
0s
#381
b00000011000000000000000000000000 3
b001 ;
b00000000000000000000000000000011 S
b00000011 k
1s
#383
0s
#385
1#
0+
b00000000000000000000000000000000 3
b000 ;
1K
b00000000000000000000000000000100 S
0[
b00000000 k
1s
#387
0s
#389
0#
1+
b00000000000000000000000000000100 3
b100 ;
0K
b00000000000000000000000000000001 S
1[
1s
#391
0s
#393
b00000000000000000000010000000000 3
b011 ;
b00000000000000000000000000000010 S
1s
#395
0s
#397
b00000000000001000000000000000000 3
b010 ;
b00000000000000000000000000000011 S
1s
#399
0s
#401
b00000100000000000000000000000000 3
b001 ;
b00000000000000000000000000000100 S
b00000100 k
1s
#403
0s
#405
1#
0+
b00000000000000000000000000000000 3
b000 ;
1K
b00000000000000000000000000000001 S
0[
b00000000 k
1s
#407
0s
#409
0#
1+
b00000000000000000000000000000001 3
b100 ;
0K
b00000000000000000000000000000010 S
1[
1s
#411
0s
#413
b00000000000000000000000100000000 3
b011 ;
b00000000000000000000000000000011 S
1s
#415
0s
#417
b00000000000000010000000000000000 3
b010 ;
b00000000000000000000000000000100 S
1s
#419
0s
#421
b00000001000000000000000000000000 3
b001 ;
b00000000000000000000000000000001 S
b00000001 k
1s
#423
0s
#425
1#
0+
b00000000000000000000000000000000 3
b000 ;
1K
b00000000000000000000000000000010 S
0[
b00000000 k
1s
#427
0s
#429
0#
1+
b00000000000000000000000000000010 3
b100 ;
0K
b00000000000000000000000000000011 S
1[
1s
#431
0s
#433
b00000000000000000000001000000000 3
b011 ;
b00000000000000000000000000000100 S
1s
#435
0s
#437
b00000000000000100000000000000000 3
b010 ;
b00000000000000000000000000000001 S
1s
#439
0s
#441
b00000010000000000000000000000000 3
b001 ;
b00000000000000000000000000000010 S
b00000010 k
1s
#443
0s
#445
1#
0+
b00000000000000000000000000000000 3
b000 ;
1K
b00000000000000000000000000000011 S
0[
b00000000 k
1s
#447
0s
#449
0#
1+
b00000000000000000000000000000011 3
b100 ;
0K
b00000000000000000000000000000100 S
1[
1s
#451
0s
#453
b00000000000000000000001100000000 3
b011 ;
b00000000000000000000000000000001 S
1s
#455
0s
#457
b00000000000000110000000000000000 3
b010 ;
b00000000000000000000000000000010 S
1s
#459
0s
#461
b00000011000000000000000000000000 3
b001 ;
b00000000000000000000000000000011 S
b00000011 k
1s
#463
0s
#465
1#
0+
b00000000000000000000000000000000 3
b000 ;
1K
b00000000000000000000000000000100 S
0[
b00000000 k
1s
#467
0s
#469
0#
1+
b00000000000000000000000000000100 3
b100 ;
0K
b00000000000000000000000000000001 S
1[
1s
#471
0s
#473
b00000000000000000000010000000000 3
b011 ;
b00000000000000000000000000000010 S
1s
#475
0s
#477
b00000000000001000000000000000000 3
b010 ;
b00000000000000000000000000000011 S
1s
#479
0s
#481
b00000100000000000000000000000000 3
b001 ;
b00000000000000000000000000000100 S
b00000100 k
1s
#483
0s
#485
0+
b00000000000000000000000000000000 3
b000 ;
0C
1K
0[
b00000000 k
1s
